chacha20poly1305_reuseable/__init__.py
chacha20poly1305_reuseable/py.typed
chacha20poly1305_reuseable-0.13.1.dist-info/LICENSE
chacha20poly1305_reuseable-0.13.1.dist-info/METADATA
chacha20poly1305_reuseable-0.13.1.dist-info/WHEEL
chacha20poly1305_reuseable-0.13.1.dist-info/RECORD
