Metadata-Version: 2.1
Name: chacha20poly1305-reuseable
Version: 0.13.1
Summary: ChaCha20Poly1305 that is reuseable for asyncio
Home-page: https://github.com/bdraco/chacha20poly1305-reuseable
License: Apache-2.0 OR BSD-3-Clause
Author: J. Nick Koston
Author-email: nick@koston.org
Requires-Python: >=3.8,<4.0
Classifier: Development Status :: 2 - Pre-Alpha
Classifier: Intended Audience :: Developers
Classifier: License :: Other/Proprietary License
Classifier: Natural Language :: English
Classifier: Operating System :: OS Independent
Classifier: Programming Language :: Python :: 3
Classifier: Programming Language :: Python :: 3.8
Classifier: Programming Language :: Python :: 3.9
Classifier: Programming Language :: Python :: 3.10
Classifier: Programming Language :: Python :: 3.11
Classifier: Programming Language :: Python :: 3.12
Classifier: Topic :: Software Development :: Libraries
Requires-Dist: cryptography (>=43.0.0)
Project-URL: Bug Tracker, https://github.com/bdraco/chacha20poly1305-reuseable/issues
Project-URL: Changelog, https://github.com/bdraco/chacha20poly1305-reuseable/blob/main/CHANGELOG.md
Project-URL: Repository, https://github.com/bdraco/chacha20poly1305-reuseable
